{
  "display": {
    "background": "minecraft:textures/block/stone.png",
    "icon": {
      "item": "super_mario:builder_box_mario"
    },
    "title": {
      "translate": "advancements.super_mario_minecraft_a.title"
    },
    "description": {
      "translate": "advancements.super_mario_minecraft_a.descr"
    },
    "frame": "goal",
    "show_toast": true,
    "announce_to_chat": true,
    "hidden": false
  },
  "criteria": {
    "super_mario_minecraft_a": {
      "trigger": "minecraft:changed_dimension",
      "conditions": {
        "to": "minecraft:overworld"
      }
    }
  },
  "rewards": {
    "experience": 0,
    "recipes": [
      "super_mario:recipe_q_block",
      "super_mario:craft_mushroom_world_portal_opener",
      "super_mario:craft_moon_portal_openere",
      "super_mario:craft_mushroom_kingdom_portal_opener",
      "super_mario:craft_portal_block",
      "super_mario:craft_flower_kingdom_portal_igniter"
    ]
  }
}